[
  {
    "id": "2025-002",
    "title": "خدمات صيانة شبكات لمباني وزارة الاتصالات",
    "entity": "وزارة الاتصالات",
    "category": "حكومية",
    "city": "الأنبار",
    "adNumber": "إعلان/شبكات/12",
    "deadline": "2026-02-01",
    "postedDate": "2025-12-14",
    "status": "مفتوح",
    "link": "#",
    "description": "صيانة شاملة للبنية التحتية للشبكات، استبدال المبدلات، تمديد كيبلات ألياف ضوئية، وفحص دوري.",
    "documentPrice": 30000,
    "currency": "IQD",
    "pickupLocation": "وزارة الاتصالات – الطابق الأرضي – المشتريات",
    "submissionPlace": "ديوان الوزارة – شباك الاستلام",
    "submissionRequirements": [
      "هوية غرفة التجارة",
      "سيرة خبرات سابقة",
      "كشف تجهيزات وفنيين"
    ],
    "notes": "الأولوية للشركات ذات الخبرة المثبتة",
    "files": [
      {
        "label": "نطاق العمل",
        "url": "#"
      }
    ],
    "contact": {
      "phone": "+964-771-0000002",
      "email": "tenders@moc.gov.iq"
    }
  },
  {
    "id": "008",
    "title": "شراء أجهزة إزالة الرطوبة لبنك الجينات في السليمانية",
    "entity": "@",
    "category": "منظمات",
    "city": "السليمانية",
    "adNumber": "NGO-TN-2026-006",
    "deadline": "2026-01-25",
    "postedDate": "2026-01-17",
    "status": "مفتوح",
    "link": "https://www.facebook.com/IraqsTenders",
    "description": "شراء أجهزة إزالة الرطوبة لبنك الجينات في السليمانية\n",
    "documentPrice": 0,
    "currency": "IQD",
    "pickupLocation": "ايتك",
    "submissionPlace": "@",
    "submissionRequirements": [
      "لمعرفة المتطلبات تواصل معنا"
    ],
    "notes": "شراء أجهزة إزالة الرطوبة لبنك الجينات في السليمانية\n",
    "files": [],
    "contact": {
      "phone": "07817823680",
      "email": "itechanbar@gmail.com"
    }
  },
  {
    "id": "009",
    "title": "شراء طاولات عمل من الفولاذ المقاوم للصدأ (لصناعة الألبان)",
    "entity": "@",
    "category": "منظمات",
    "city": "@",
    "adNumber": "NGO-TN-2026-007",
    "deadline": "2026-01-26",
    "postedDate": "2026-01-17",
    "status": "مفتوح",
    "link": "https://www.facebook.com/IraqsTenders",
    "description": "شراء طاولات عمل من الفولاذ المقاوم للصدأ (لصناعة الألبان)\n",
    "documentPrice": 0,
    "currency": "IQD",
    "pickupLocation": "ايتك",
    "submissionPlace": "@",
    "submissionRequirements": [
      "@"
    ],
    "notes": "@",
    "files": [],
    "contact": {
      "phone": "07817823680",
      "email": "itechanbar@gmail.com"
    }
  }
]